wordchain/__init__.py
wordchain/errors.py
wordchain/py.typed
wordchain/version.py
wordchain/wordchain.py
python_wordchain-0.4.2.dist-info/METADATA
python_wordchain-0.4.2.dist-info/WHEEL
python_wordchain-0.4.2.dist-info/licenses/LICENSE
python_wordchain-0.4.2.dist-info/RECORD
