Metadata-Version: 2.3
Name: python-wordchain
Version: 0.4.2
Summary: A package to build word chains from a given list of words.
License-File: LICENSE
Requires-Python: >=3.8
Requires-Dist: networkx>=2.5.1
